tsview/__init__.py
tsview/app.py
tsview/blueprint.py
tsview/cli.py
tsview/horizon.py
tsview/icons.py
tsview/menu.py
tsview/migrate.py
tsview/moment.py
tsview/schema.py
tsview/schema.sql
tsview/table.py
tsview/util.py
tsview/tsview_static/ace.js
tsview/tsview_static/ace_editor.js
tsview/tsview_static/addformulas_elm.css
tsview/tsview_static/addformulas_elm.js
tsview/tsview_static/arrow_outward.png
tsview/tsview_static/bootstrap.min.css
tsview/tsview_static/cache_elm.js
tsview/tsview_static/delete_elm.js
tsview/tsview_static/editor.css
tsview/tsview_static/editor_tree.js
tsview/tsview_static/formula_elm.css
tsview/tsview_static/formula_elm.js
tsview/tsview_static/formulas_elm.js
tsview/tsview_static/grid.png
tsview/tsview_static/groupinfo_elm.js
tsview/tsview_static/homepage_elm.css
tsview/tsview_static/homepage_elm.js
tsview/tsview_static/loading_wheel.gif
tsview/tsview_static/logo-pythonian.png
tsview/tsview_static/logo.jpg
tsview/tsview_static/menu_elm.css
tsview/tsview_static/menu_stand_alone.css
tsview/tsview_static/menu_stand_alone_elm.js
tsview/tsview_static/mode-lisp.js
tsview/tsview_static/operators.css
tsview/tsview_static/operators_elm.js
tsview/tsview_static/plot.png
tsview/tsview_static/plot_elm.js
tsview/tsview_static/plot_figure.js
tsview/tsview_static/pygmentize.css
tsview/tsview_static/qeditor_elm.js
tsview/tsview_static/search_elm.js
tsview/tsview_static/settings_elm.js
tsview/tsview_static/style.css
tsview/tsview_static/theme-xcode.js
tsview/tsview_static/tree.css
tsview/tsview_static/tseditor.css
tsview/tsview_static/tseditor_elm.js
tsview/tsview_static/tsinfo_elm.js
tsview/tsview_static/util.js
tsview/tsview_templates/addformulas.html
tsview/tsview_templates/cache.html
tsview/tsview_templates/formulas.html
tsview/tsview_templates/groupinfo.html
tsview/tsview_templates/homepage.html
tsview/tsview_templates/menu.html
tsview/tsview_templates/menu_stand_alone.html
tsview/tsview_templates/operators.html
tsview/tsview_templates/plot_figure.js.html
tsview-0.20.1.dist-info/LICENSE
tsview-0.20.1.dist-info/METADATA
tsview-0.20.1.dist-info/WHEEL
tsview-0.20.1.dist-info/entry_points.txt
tsview-0.20.1.dist-info/top_level.txt
tsview-0.20.1.dist-info/RECORD
