Metadata-Version: 2.1
Name: tsview
Version: 0.20.1
Summary: Plugin to `tshistory` which provides a `view` subcommand to visualize time series
Home-page: https://hg.sr.ht/~pythonian/tsview
Author: Pythonian
Author-email: aurelien.campeas@pythonian.fr,andre.espaze@pythonian.fr,arnaud.campeas@pythonian.frauguste.pezin@pythonian.fr
Classifier: Development Status :: 4 - Beta
Classifier: Intended Audience :: Developers
Classifier: License :: OSI Approved :: GNU Lesser General Public License v3 (LGPLv3)
Classifier: Operating System :: OS Independent
Classifier: Programming Language :: Python :: 3
Classifier: Topic :: Database
Classifier: Topic :: Scientific/Engineering
Classifier: Topic :: Software Development :: Version Control
Classifier: Topic :: Scientific/Engineering :: Visualization
License-File: LICENSE
Requires-Dist: flask ==2.3.3
Requires-Dist: werkzeug
Requires-Dist: pytest-sa-pg
Requires-Dist: tshistory >=0.19.4
Requires-Dist: plotly <6.0
Requires-Dist: tshistory-formula >=0.15
